isosplit6_cpp.cpython-39-x86_64-linux-gnu.so
isosplit6/__init__.py
isosplit6/tests/test_simple_run.py
isosplit6/tests/__init__.py
isosplit6-0.1.4.dist-info/top_level.txt
isosplit6-0.1.4.dist-info/WHEEL
isosplit6-0.1.4.dist-info/METADATA
isosplit6-0.1.4.dist-info/LICENSE
isosplit6-0.1.4.dist-info/RECORD
