Metadata-Version: 2.1
Name: isosplit6
Version: 0.1.4
Summary: None
Home-page: https://github.com/magland/isosplit6
Author: Jeremy Magland
Author-email: jmagland@flatironinstitute.org
Project-URL: Bug Tracker, https://github.com/magland/isosplit6/issues
License-File: LICENSE
